LICENSE
README.md
pyproject.toml
setup.py
src/add_xqm/__init__.py
src/add_xqm/add.py
src/add_xqm.egg-info/PKG-INFO
src/add_xqm.egg-info/SOURCES.txt
src/add_xqm.egg-info/dependency_links.txt
src/add_xqm.egg-info/top_level.txt