Metadata-Version: 2.4
Name: add_xqm
Version: 1.0.1
Summary: xxx
Home-page: https://github.com/hujinpu/add_xqm
Author: yunyi
Author-email: 2523863783@qq.com
Requires-Python: >=3.6
License-File: LICENSE
Dynamic: author
Dynamic: author-email
Dynamic: description
Dynamic: description-content-type
Dynamic: home-page
Dynamic: license-file
Dynamic: requires-python
Dynamic: summary
